{"version":"1","myst":"1.6.0","references":[{"kind":"page","data":"/index.json","url":"/"},{"identifier":"motivation","kind":"heading","data":"/index.json","url":"/","implicit":true},{"identifier":"authors","kind":"heading","data":"/index.json","url":"/","implicit":true},{"identifier":"contributors","kind":"heading","data":"/index.json","url":"/","implicit":true},{"identifier":"structure","kind":"heading","data":"/index.json","url":"/","implicit":true},{"identifier":"introduction","kind":"heading","data":"/index.json","url":"/","implicit":true},{"identifier":"data-preprocessing","kind":"heading","data":"/index.json","url":"/","implicit":true},{"identifier":"training-the-model","kind":"heading","data":"/index.json","url":"/","implicit":true},{"identifier":"running-the-notebooks","kind":"heading","data":"/index.json","url":"/","implicit":true},{"identifier":"running-on-binder","kind":"heading","data":"/index.json","url":"/","implicit":true},{"identifier":"running-on-your-own-machine","kind":"heading","data":"/index.json","url":"/","implicit":true},{"kind":"page","data":"/notebooks.how-to-cite.json","url":"/notebooks/how-to-cite"},{"kind":"page","data":"/notebooks.ibtrack-preprocessing.json","url":"/notebooks/ibtrack-preprocessing"},{"identifier":"overview","kind":"heading","data":"/notebooks.ibtrack-preprocessing.json","url":"/notebooks/ibtrack-preprocessing","implicit":true},{"identifier":"prerequisites","kind":"heading","data":"/notebooks.ibtrack-preprocessing.json","url":"/notebooks/ibtrack-preprocessing","implicit":true},{"identifier":"imports","kind":"heading","data":"/notebooks.ibtrack-preprocessing.json","url":"/notebooks/ibtrack-preprocessing","implicit":true},{"identifier":"read-in-ibtracks-data","kind":"heading","data":"/notebooks.ibtrack-preprocessing.json","url":"/notebooks/ibtrack-preprocessing","implicit":true},{"identifier":"method-to-preprocess-the-track-data","kind":"heading","data":"/notebooks.ibtrack-preprocessing.json","url":"/notebooks/ibtrack-preprocessing","implicit":true},{"identifier":"process-ibtracks-data-using-the-above-methods","kind":"heading","data":"/notebooks.ibtrack-preprocessing.json","url":"/notebooks/ibtrack-preprocessing","implicit":true},{"identifier":"organize-the-edited-ibtracks-file","kind":"heading","data":"/notebooks.ibtrack-preprocessing.json","url":"/notebooks/ibtrack-preprocessing","implicit":true},{"identifier":"see-the-organized-and-edited-ibtracks-file","kind":"heading","data":"/notebooks.ibtrack-preprocessing.json","url":"/notebooks/ibtrack-preprocessing","implicit":true},{"identifier":"plot-the-track-data-we-have-edited-and-organized","kind":"heading","data":"/notebooks.ibtrack-preprocessing.json","url":"/notebooks/ibtrack-preprocessing","implicit":true},{"identifier":"summary","kind":"heading","data":"/notebooks.ibtrack-preprocessing.json","url":"/notebooks/ibtrack-preprocessing","implicit":true},{"identifier":"whats-next","kind":"heading","data":"/notebooks.ibtrack-preprocessing.json","url":"/notebooks/ibtrack-preprocessing","implicit":true},{"identifier":"resources-and-references","kind":"heading","data":"/notebooks.ibtrack-preprocessing.json","url":"/notebooks/ibtrack-preprocessing","implicit":true},{"kind":"page","data":"/notebooks.era5-preprocessing.json","url":"/notebooks/era5-preprocessing"},{"identifier":"overview","kind":"heading","data":"/notebooks.era5-preprocessing.json","url":"/notebooks/era5-preprocessing","implicit":true},{"identifier":"prerequisites","kind":"heading","data":"/notebooks.era5-preprocessing.json","url":"/notebooks/era5-preprocessing","implicit":true},{"identifier":"imports","kind":"heading","data":"/notebooks.era5-preprocessing.json","url":"/notebooks/era5-preprocessing","implicit":true},{"identifier":"your-first-content-section","kind":"heading","data":"/notebooks.era5-preprocessing.json","url":"/notebooks/era5-preprocessing","implicit":true},{"identifier":"a-content-subsection","kind":"heading","data":"/notebooks.era5-preprocessing.json","url":"/notebooks/era5-preprocessing","implicit":true},{"identifier":"another-content-subsection","kind":"heading","data":"/notebooks.era5-preprocessing.json","url":"/notebooks/era5-preprocessing","implicit":true},{"identifier":"your-second-content-section","kind":"heading","data":"/notebooks.era5-preprocessing.json","url":"/notebooks/era5-preprocessing","implicit":true},{"identifier":"a-subsection-to-the-second-section","kind":"heading","data":"/notebooks.era5-preprocessing.json","url":"/notebooks/era5-preprocessing","implicit":true},{"identifier":"a-quick-demonstration","kind":"heading","data":"/notebooks.era5-preprocessing.json","url":"/notebooks/era5-preprocessing","implicit":true},{"identifier":"of-further-and-further","kind":"heading","data":"/notebooks.era5-preprocessing.json","url":"/notebooks/era5-preprocessing","implicit":true},{"identifier":"header-levels","kind":"heading","data":"/notebooks.era5-preprocessing.json","url":"/notebooks/era5-preprocessing","implicit":true},{"identifier":"last-section","kind":"heading","data":"/notebooks.era5-preprocessing.json","url":"/notebooks/era5-preprocessing","implicit":true},{"identifier":"summary","kind":"heading","data":"/notebooks.era5-preprocessing.json","url":"/notebooks/era5-preprocessing","implicit":true},{"identifier":"whats-next","kind":"heading","data":"/notebooks.era5-preprocessing.json","url":"/notebooks/era5-preprocessing","implicit":true},{"identifier":"resources-and-references","kind":"heading","data":"/notebooks.era5-preprocessing.json","url":"/notebooks/era5-preprocessing","implicit":true}]}