{"version":2,"kind":"Notebook","sha256":"1e5b2196467cf329cfbc1d89c76f2a5f044d8db026e9ff163e9d3210d0c91819","slug":"notebooks.era5-preprocessing","location":"/notebooks/era5_preprocessing.ipynb","dependencies":[],"frontmatter":{"title":"ERA5 Data Preprocessing","content_includes_title":false,"kernelspec":{"name":"python3","display_name":"Python 3 (ipykernel)","language":"python"},"authors":[{"nameParsed":{"literal":"Nirmal Alex, Matthew Lynne","given":"Matthew Lynne","family":"Nirmal Alex"},"name":"Nirmal Alex, Matthew Lynne","id":"contributors-myst-generated-uid-0"}],"open_access":true,"license":{"content":{"id":"CC-BY-4.0","url":"https://creativecommons.org/licenses/by/4.0/","name":"Creative Commons Attribution 4.0 International","free":true,"CC":true},"code":{"id":"Apache-2.0","url":"https://opensource.org/licenses/Apache-2.0","name":"Apache License 2.0","free":true,"osi":true}},"github":"https://github.com/ProjectPythia/ml-hurricane-intensity","copyright":"2024","affiliations":[{"id":"UAlbany","name":"University at Albany (SUNY)","department":"Atmospheric and Environmental Sciences","url":"https://www.albany.edu/daes"},{"id":"CISL","name":"NSF National Center for Atmospheric Research","department":"Computational and Information Systems Lab","url":"https://www.cisl.ucar.edu"},{"id":"Unidata","name":"NSF Unidata","url":"https://www.unidata.ucar.edu"},{"id":"Argonne","name":"Argonne National Laboratory","department":"Environmental Science Division","url":"https://www.anl.gov/evs"},{"id":"CarbonPlan","name":"CarbonPlan","url":"https://carbonplan.org"},{"id":"NVIDIA","name":"NVIDIA Corporation","url":"https://www.nvidia.com/"}],"numbering":{"title":{"offset":1}},"edit_url":"https://github.com/ProjectPythia/ml-hurricane-intensity/blob/HEAD/notebooks/era5_preprocessing.ipynb","exports":[{"format":"ipynb","filename":"era5_preprocessing.ipynb","url":"/ml-hurricane-intensity/_preview/23/build/era5_preprocessing-0ffd91ab6ac3886243a4b3cfbb615f30.ipynb"}]},"widgets":{},"mdast":{"type":"root","children":[{"type":"block","kind":"notebook-content","children":[{"type":"thematicBreak","position":{"start":{"line":1,"column":1},"end":{"line":1,"column":1}},"key":"vu1m9vxYrw"}],"key":"VfLKKlbONc"},{"type":"block","kind":"notebook-content","children":[{"type":"heading","depth":2,"position":{"start":{"line":1,"column":1},"end":{"line":1,"column":1}},"children":[{"type":"text","value":"Overview","position":{"start":{"line":1,"column":1},"end":{"line":1,"column":1}},"key":"t5OoHOCXeE"}],"identifier":"overview","label":"Overview","html_id":"overview","implicit":true,"key":"qxJU8AYYkm"},{"type":"paragraph","position":{"start":{"line":2,"column":1},"end":{"line":2,"column":1}},"children":[{"type":"text","value":"Here, we will use the processed IBTRACKS data to select ERA5 environmental variables associated with each cyclone.","position":{"start":{"line":2,"column":1},"end":{"line":2,"column":1}},"key":"KtP8B0ZH4F"}],"key":"SQdM0RBrVi"}],"key":"Ga3v8idAvE"},{"type":"block","kind":"notebook-content","children":[{"type":"heading","depth":2,"position":{"start":{"line":1,"column":1},"end":{"line":1,"column":1}},"children":[{"type":"text","value":"Prerequisites","position":{"start":{"line":1,"column":1},"end":{"line":1,"column":1}},"key":"RUdbuJOxjN"}],"identifier":"prerequisites","label":"Prerequisites","html_id":"prerequisites","implicit":true,"key":"cRiziO58wC"},{"type":"table","position":{"start":{"line":2,"column":1},"end":{"line":7,"column":1}},"children":[{"type":"tableRow","position":{"start":{"line":2,"column":1},"end":{"line":2,"column":1}},"children":[{"type":"tableCell","header":true,"position":{"start":{"line":2,"column":1},"end":{"line":2,"column":1}},"children":[{"type":"text","value":"Concepts","position":{"start":{"line":2,"column":1},"end":{"line":2,"column":1}},"key":"JFyeGXin5V"}],"key":"u2GUWoy2dm"},{"type":"tableCell","header":true,"position":{"start":{"line":2,"column":1},"end":{"line":2,"column":1}},"children":[{"type":"text","value":"Importance","position":{"start":{"line":2,"column":1},"end":{"line":2,"column":1}},"key":"jymbPxTF7N"}],"key":"Q3BVPFRFVj"},{"type":"tableCell","header":true,"position":{"start":{"line":2,"column":1},"end":{"line":2,"column":1}},"children":[{"type":"text","value":"Notes","position":{"start":{"line":2,"column":1},"end":{"line":2,"column":1}},"key":"xds1p3W5mm"}],"key":"xeTBiHTKO0"}],"key":"h5YNHih74s"},{"type":"tableRow","position":{"start":{"line":4,"column":1},"end":{"line":4,"column":1}},"children":[{"type":"tableCell","position":{"start":{"line":4,"column":1},"end":{"line":4,"column":1}},"children":[{"type":"link","url":"https://foundations.projectpythia.org/core/numpy/","position":{"start":{"line":4,"column":1},"end":{"line":4,"column":1}},"children":[{"type":"text","value":"Intro to NUMPY","position":{"start":{"line":4,"column":1},"end":{"line":4,"column":1}},"key":"gVx1Nlf047"}],"urlSource":"https://foundations.projectpythia.org/core/numpy/","key":"BwwyNAw07S"}],"key":"f3eIAeVqhd"},{"type":"tableCell","position":{"start":{"line":4,"column":1},"end":{"line":4,"column":1}},"children":[{"type":"text","value":"Necessary","position":{"start":{"line":4,"column":1},"end":{"line":4,"column":1}},"key":"QDvlGhUDdz"}],"key":"QVT4aZM6dW"},{"type":"tableCell","position":{"start":{"line":4,"column":1},"end":{"line":4,"column":1}},"children":[],"key":"QWgiJTkulp"}],"key":"sVRc3diYTZ"},{"type":"tableRow","position":{"start":{"line":5,"column":1},"end":{"line":5,"column":1}},"children":[{"type":"tableCell","position":{"start":{"line":5,"column":1},"end":{"line":5,"column":1}},"children":[{"type":"link","url":"https://foundations.projectpythia.org/core/numpy/","position":{"start":{"line":5,"column":1},"end":{"line":5,"column":1}},"children":[{"type":"text","value":"Intro to PANDAS","position":{"start":{"line":5,"column":1},"end":{"line":5,"column":1}},"key":"gt2eNtPb3N"}],"urlSource":"https://foundations.projectpythia.org/core/numpy/","key":"E1iYtz9a8X"}],"key":"Wbc6T6JHTT"},{"type":"tableCell","position":{"start":{"line":5,"column":1},"end":{"line":5,"column":1}},"children":[{"type":"text","value":"Necessary","position":{"start":{"line":5,"column":1},"end":{"line":5,"column":1}},"key":"Fyopcn1r65"}],"key":"ZtakLk2TBb"},{"type":"tableCell","position":{"start":{"line":5,"column":1},"end":{"line":5,"column":1}},"children":[],"key":"JiaMD9DnpR"}],"key":"siQejTTz6h"},{"type":"tableRow","position":{"start":{"line":6,"column":1},"end":{"line":6,"column":1}},"children":[{"type":"tableCell","position":{"start":{"line":6,"column":1},"end":{"line":6,"column":1}},"children":[{"type":"link","url":"https://foundations.projectpythia.org/core/xarray/","position":{"start":{"line":6,"column":1},"end":{"line":6,"column":1}},"children":[{"type":"text","value":"Intro to XARRAY","position":{"start":{"line":6,"column":1},"end":{"line":6,"column":1}},"key":"JgMhmBsEzv"}],"urlSource":"https://foundations.projectpythia.org/core/xarray/","key":"ieQjzlwuaU"}],"key":"MkKz19H8pW"},{"type":"tableCell","position":{"start":{"line":6,"column":1},"end":{"line":6,"column":1}},"children":[{"type":"text","value":"Necessary","position":{"start":{"line":6,"column":1},"end":{"line":6,"column":1}},"key":"hSC0jHcGLs"}],"key":"QtCMkz8rAg"},{"type":"tableCell","position":{"start":{"line":6,"column":1},"end":{"line":6,"column":1}},"children":[],"key":"meaMvqFk9b"}],"key":"OGwb75gQ0m"},{"type":"tableRow","position":{"start":{"line":7,"column":1},"end":{"line":7,"column":1}},"children":[{"type":"tableCell","position":{"start":{"line":7,"column":1},"end":{"line":7,"column":1}},"children":[{"type":"text","value":"Project management","position":{"start":{"line":7,"column":1},"end":{"line":7,"column":1}},"key":"XgHlnLCoAx"}],"key":"sSWkwt3ICd"},{"type":"tableCell","position":{"start":{"line":7,"column":1},"end":{"line":7,"column":1}},"children":[{"type":"text","value":"Helpful","position":{"start":{"line":7,"column":1},"end":{"line":7,"column":1}},"key":"J5na08je6J"}],"key":"FNHGUntvG1"},{"type":"tableCell","position":{"start":{"line":7,"column":1},"end":{"line":7,"column":1}},"children":[],"key":"OH6xC31Fej"}],"key":"uMTgvZuw9k"}],"key":"SKZGG7GuuI"},{"type":"list","ordered":false,"spread":false,"position":{"start":{"line":9,"column":1},"end":{"line":13,"column":1}},"children":[{"type":"listItem","spread":true,"position":{"start":{"line":9,"column":1},"end":{"line":9,"column":1}},"children":[{"type":"strong","position":{"start":{"line":9,"column":1},"end":{"line":9,"column":1}},"children":[{"type":"text","value":"Time to learn","position":{"start":{"line":9,"column":1},"end":{"line":9,"column":1}},"key":"Bw40KCCnIS"}],"key":"Wx7WOrD8Ob"},{"type":"text","value":": estimate in minutes. For a rough idea, use 5 mins per subsection, 10 if longer; add these up for a total. Safer to round up and overestimate.","position":{"start":{"line":9,"column":1},"end":{"line":9,"column":1}},"key":"Wdxmts3q5J"}],"key":"i3MuJfhTTz"},{"type":"listItem","spread":true,"position":{"start":{"line":10,"column":1},"end":{"line":13,"column":1}},"children":[{"type":"strong","position":{"start":{"line":10,"column":1},"end":{"line":10,"column":1}},"children":[{"type":"text","value":"System requirements","position":{"start":{"line":10,"column":1},"end":{"line":10,"column":1}},"key":"hSt7IRawB2"}],"key":"rbk5kxUTnT"},{"type":"text","value":":","position":{"start":{"line":10,"column":1},"end":{"line":10,"column":1}},"key":"LxIlVBPJdf"},{"type":"list","ordered":false,"spread":false,"position":{"start":{"line":11,"column":1},"end":{"line":13,"column":1}},"children":[{"type":"listItem","spread":true,"position":{"start":{"line":11,"column":1},"end":{"line":11,"column":1}},"children":[{"type":"text","value":"Populate with any system, version, or non-Python software requirements if necessary","position":{"start":{"line":11,"column":1},"end":{"line":11,"column":1}},"key":"tW0Bi82JJJ"}],"key":"OWMqYtuwl9"},{"type":"listItem","spread":true,"position":{"start":{"line":12,"column":1},"end":{"line":12,"column":1}},"children":[{"type":"text","value":"Otherwise use the concepts table above and the Imports section below to describe required packages as necessary","position":{"start":{"line":12,"column":1},"end":{"line":12,"column":1}},"key":"EYlOA9kJVS"}],"key":"TRkp0elD8N"},{"type":"listItem","spread":true,"position":{"start":{"line":13,"column":1},"end":{"line":13,"column":1}},"children":[{"type":"text","value":"If no extra requirements, remove the ","position":{"start":{"line":13,"column":1},"end":{"line":13,"column":1}},"key":"ZpoV2Sj8MM"},{"type":"strong","position":{"start":{"line":13,"column":1},"end":{"line":13,"column":1}},"children":[{"type":"text","value":"System requirements","position":{"start":{"line":13,"column":1},"end":{"line":13,"column":1}},"key":"Qgn5V2vpML"}],"key":"IsHlePnz5u"},{"type":"text","value":" point altogether","position":{"start":{"line":13,"column":1},"end":{"line":13,"column":1}},"key":"bXV8XL1yAz"}],"key":"SEdgytK4Fy"}],"key":"Www1g27vHs"}],"key":"hbSIQdZFn8"}],"key":"dsITbCP2Hy"}],"key":"H3kq6hGEMe"},{"type":"block","kind":"notebook-content","children":[{"type":"thematicBreak","position":{"start":{"line":1,"column":1},"end":{"line":1,"column":1}},"key":"EJ1vfKajQe"}],"key":"wOnpoT2KlB"},{"type":"block","kind":"notebook-content","children":[{"type":"heading","depth":2,"position":{"start":{"line":1,"column":1},"end":{"line":1,"column":1}},"children":[{"type":"text","value":"Imports","position":{"start":{"line":1,"column":1},"end":{"line":1,"column":1}},"key":"DCnNiYRoas"}],"identifier":"imports","label":"Imports","html_id":"imports","implicit":true,"key":"EMZO8vRlmJ"},{"type":"paragraph","position":{"start":{"line":2,"column":1},"end":{"line":2,"column":1}},"children":[{"type":"text","value":"Begin your body of content with another ","position":{"start":{"line":2,"column":1},"end":{"line":2,"column":1}},"key":"lRdAh92Hdj"},{"type":"inlineCode","value":"---","position":{"start":{"line":2,"column":1},"end":{"line":2,"column":1}},"key":"DSEqzq0Nwe"},{"type":"text","value":" divider before continuing into this section, then remove this body text and populate the following code cell with all necessary Python imports ","position":{"start":{"line":2,"column":1},"end":{"line":2,"column":1}},"key":"m4OyrNHzTl"},{"type":"strong","position":{"start":{"line":2,"column":1},"end":{"line":2,"column":1}},"children":[{"type":"text","value":"up-front","position":{"start":{"line":2,"column":1},"end":{"line":2,"column":1}},"key":"V8WUiSV84h"}],"key":"rBhjtQNqCE"},{"type":"text","value":":","position":{"start":{"line":2,"column":1},"end":{"line":2,"column":1}},"key":"QvfQKoLIQf"}],"key":"eC5sWzgRcO"}],"key":"UW53uTAvrg"},{"type":"block","kind":"notebook-code","children":[{"type":"code","lang":"python","executable":true,"value":"import xarray as xr \nfrom dask.distributed import Client\nimport matplotlib.pyplot as plt\nimport cartopy.crs as ccrs\nimport pandas as pd\nimport glob\nfrom global_land_mask import globe\nimport cartopy.feature as cfeature\nfrom matplotlib.path import Path\nimport matplotlib.patches as patches\nfrom matplotlib import patheffects\nimport numpy as np\nimport dask","key":"QjPyvez2Fg"},{"type":"output","id":"P2iH8KE-i4KWnbkQrC1iv","data":[],"key":"w6GhBo9rfF"}],"key":"AVWq65saAh"},{"type":"block","kind":"notebook-content","children":[{"type":"heading","depth":2,"position":{"start":{"line":1,"column":1},"end":{"line":1,"column":1}},"children":[{"type":"text","value":"Edit and pad ERA5 data","position":{"start":{"line":1,"column":1},"end":{"line":1,"column":1}},"key":"NSJuX7Z0i4"}],"identifier":"edit-and-pad-era5-data","label":"Edit and pad ERA5 data","html_id":"edit-and-pad-era5-data","implicit":true,"key":"XvaK3UHgQL"}],"key":"WTZfpwonwR"},{"type":"block","kind":"notebook-content","children":[{"type":"paragraph","position":{"start":{"line":1,"column":1},"end":{"line":1,"column":1}},"children":[{"type":"text","value":"In this section, we will select ERA5 data within a 5x5 latitude/longitude grid centered at each cyclone center at each time step in our dataset. We will then have to pad the data to account for instances in which grid cells occur over land.","position":{"start":{"line":1,"column":1},"end":{"line":1,"column":1}},"key":"W5XFG2LMX7"}],"key":"xWfrqIWVl9"}],"key":"Q0UKxDyCyc"},{"type":"block","kind":"notebook-code","children":[{"type":"code","lang":"python","executable":true,"value":"input_dsets = xr.open_dataset('../test_folder/final_proc_5yr_6h.nc')","key":"SClnhRE1Nx"},{"type":"output","id":"EyNKj-mVgCVUrTJZ1R84w","data":[{"output_type":"error","traceback":"\u001b[31m---------------------------------------------------------------------------\u001b[39m\n\u001b[31mValueError\u001b[39m                                Traceback (most recent call last)\n\u001b[36mCell\u001b[39m\u001b[36m \u001b[39m\u001b[32mIn[2]\u001b[39m\u001b[32m, line 1\u001b[39m\n\u001b[32m----> \u001b[39m\u001b[32m1\u001b[39m input_dsets = \u001b[43mxr\u001b[49m\u001b[43m.\u001b[49m\u001b[43mopen_dataset\u001b[49m\u001b[43m(\u001b[49m\u001b[33;43m'\u001b[39;49m\u001b[33;43m../test_folder/final_proc_5yr_6h.nc\u001b[39;49m\u001b[33;43m'\u001b[39;49m\u001b[43m)\u001b[49m\n\n\u001b[36mFile \u001b[39m\u001b[32m~/micromamba/envs/cookbook-dev/lib/python3.12/site-packages/xarray/backends/api.py:696\u001b[39m, in \u001b[36mopen_dataset\u001b[39m\u001b[34m(filename_or_obj, engine, chunks, cache, decode_cf, mask_and_scale, decode_times, decode_timedelta, use_cftime, concat_characters, decode_coords, drop_variables, create_default_indexes, inline_array, chunked_array_type, from_array_kwargs, backend_kwargs, **kwargs)\u001b[39m\n\u001b[32m    693\u001b[39m     kwargs.update(backend_kwargs)\n\u001b[32m    695\u001b[39m \u001b[38;5;28;01mif\u001b[39;00m engine \u001b[38;5;129;01mis\u001b[39;00m \u001b[38;5;28;01mNone\u001b[39;00m:\n\u001b[32m--> \u001b[39m\u001b[32m696\u001b[39m     engine = \u001b[43mplugins\u001b[49m\u001b[43m.\u001b[49m\u001b[43mguess_engine\u001b[49m\u001b[43m(\u001b[49m\u001b[43mfilename_or_obj\u001b[49m\u001b[43m)\u001b[49m\n\u001b[32m    698\u001b[39m \u001b[38;5;28;01mif\u001b[39;00m from_array_kwargs \u001b[38;5;129;01mis\u001b[39;00m \u001b[38;5;28;01mNone\u001b[39;00m:\n\u001b[32m    699\u001b[39m     from_array_kwargs = {}\n\n\u001b[36mFile \u001b[39m\u001b[32m~/micromamba/envs/cookbook-dev/lib/python3.12/site-packages/xarray/backends/plugins.py:194\u001b[39m, in \u001b[36mguess_engine\u001b[39m\u001b[34m(store_spec)\u001b[39m\n\u001b[32m    186\u001b[39m \u001b[38;5;28;01melse\u001b[39;00m:\n\u001b[32m    187\u001b[39m     error_msg = (\n\u001b[32m    188\u001b[39m         \u001b[33m\"\u001b[39m\u001b[33mfound the following matches with the input file in xarray\u001b[39m\u001b[33m'\u001b[39m\u001b[33ms IO \u001b[39m\u001b[33m\"\u001b[39m\n\u001b[32m    189\u001b[39m         \u001b[33mf\u001b[39m\u001b[33m\"\u001b[39m\u001b[33mbackends: \u001b[39m\u001b[38;5;132;01m{\u001b[39;00mcompatible_engines\u001b[38;5;132;01m}\u001b[39;00m\u001b[33m. But their dependencies may not be installed, see:\u001b[39m\u001b[38;5;130;01m\\n\u001b[39;00m\u001b[33m\"\u001b[39m\n\u001b[32m    190\u001b[39m         \u001b[33m\"\u001b[39m\u001b[33mhttps://docs.xarray.dev/en/stable/user-guide/io.html \u001b[39m\u001b[38;5;130;01m\\n\u001b[39;00m\u001b[33m\"\u001b[39m\n\u001b[32m    191\u001b[39m         \u001b[33m\"\u001b[39m\u001b[33mhttps://docs.xarray.dev/en/stable/getting-started-guide/installing.html\u001b[39m\u001b[33m\"\u001b[39m\n\u001b[32m    192\u001b[39m     )\n\u001b[32m--> \u001b[39m\u001b[32m194\u001b[39m \u001b[38;5;28;01mraise\u001b[39;00m \u001b[38;5;167;01mValueError\u001b[39;00m(error_msg)\n\n\u001b[31mValueError\u001b[39m: did not find a match in any of xarray's currently installed IO backends ['netcdf4', 'h5netcdf', 'scipy']. Consider explicitly selecting one of the installed engines via the ``engine`` parameter, or installing additional IO dependencies, see:\nhttps://docs.xarray.dev/en/stable/getting-started-guide/installing.html\nhttps://docs.xarray.dev/en/stable/user-guide/io.html","ename":"ValueError","evalue":"did not find a match in any of xarray's currently installed IO backends ['netcdf4', 'h5netcdf', 'scipy']. Consider explicitly selecting one of the installed engines via the ``engine`` parameter, or installing additional IO dependencies, see:\nhttps://docs.xarray.dev/en/stable/getting-started-guide/installing.html\nhttps://docs.xarray.dev/en/stable/user-guide/io.html"}],"key":"VJtSYjovEX"}],"key":"rDTRlF5a4k"},{"type":"block","kind":"notebook-code","children":[{"type":"code","lang":"python","executable":true,"value":"ib_data_processed_6h = pd.read_csv('../test_folder/ib_data_processed_6h.csv')","key":"wXlwuWGuMp"},{"type":"output","id":"Gm-H19sOtVVOYbYZ9AuW9","data":[],"key":"DINwehclwV"}],"key":"U08AYeRqMD"},{"type":"block","kind":"notebook-code","children":[{"type":"code","lang":"python","executable":true,"value":"final_data = []\nmax_len = ib_data_processed_6h.groupby('id').size().max()  # assuming max length is 3 hours per storm","key":"SObNdXgb8U"},{"type":"output","id":"o0VnBLH-XwyQOCLfJMY3Q","data":[],"key":"czqunjaYzC"}],"key":"rb69emuaxK"},{"type":"block","kind":"notebook-code","children":[{"type":"code","lang":"python","executable":true,"value":"for id_number,group in ib_data_processed_6h.groupby('id'):\n    events_data = []\n    for index,row in group.iterrows():\n        lat = int(row['LAT'])\n        lon = int(row['LON'])\n        time = row['datetime']\n        \n        #We want data in a 5x5 latitude/longitude grid centered on the cyclone latitude/longitude\n        latmin = lat - 2\n        latmax = lat + 2\n        lonmin = lon - 2\n        lonmax = lon + 2\n        sel_data = input_dsets.sel(latitude=slice(latmax, latmin), longitude=slice(lonmin, lonmax), time=time)\n        \n            \n        final_xr = sel_data.rename({'latitude': 'y', 'longitude': 'x'})\n        final_xr['x'] = np.arange(0,final_xr.sizes['x'])\n        final_xr['y'] = np.arange(0,final_xr.sizes['y'])\n        \n        # fill NaN values with zeros along the x and y dimensions\n        for jj in final_xr.data_vars:\n            final_xr[jj].fillna(0)  # Fill NaN values\n        \n        #Recall that we are trying to predict the wind speed.\n        #Hence, our target is USA_WIND\n        final_xr['target'] = row['USA_WIND']    \n        events_data.append(final_xr)\n    \n    final_event = xr.concat(events_data,dim='time')\n    id\n    #Pad data with zeros up to the maximum time\n    if len(final_event.time) <= max_len:\n        new_time = pd.date_range(start=final_event['time'].min().values, periods=max_len ,freq='6h')\n        padded_data = final_event.reindex(time=new_time, fill_value=0.0)\n    else:\n        padded_data = final_event\n    \n    lead_time = np.arange(0,max_len*6 ,6)\n    padded_data['lead'] = ('time', lead_time)\n    padded_data = padded_data.assign_coords({'lead': padded_data['lead'].astype(int)})\n    \n    # swap time and lead dimensions\n    padded_data = padded_data.swap_dims({'time': 'lead'})\n    padded_data['id'] = id_number \n    \n    # convert the time dimension to a variable\n    final_data.append(padded_data)","key":"WEP8hqeyDE"},{"type":"output","id":"S9xwtxbgWo10YJIuCf2IK","data":[],"key":"l9vQmWe8qS"}],"key":"s8LD5MwrAJ"},{"type":"block","kind":"notebook-code","children":[{"type":"code","lang":"python","executable":true,"value":"final_input_padded = xr.concat(final_data, dim='SID')\nfinal_input_padded","key":"kE6bP9Kz1R"},{"type":"output","id":"4plPYpvSdpiUct8gF56Rf","data":[],"key":"mcW25NJX6k"}],"key":"VUD5yjwbwn"},{"type":"block","kind":"notebook-content","children":[{"type":"heading","depth":2,"position":{"start":{"line":1,"column":1},"end":{"line":1,"column":1}},"children":[{"type":"text","value":"Edit predictands for each cyclone","position":{"start":{"line":1,"column":1},"end":{"line":1,"column":1}},"key":"ZzGsOq9FpQ"}],"identifier":"edit-predictands-for-each-cyclone","label":"Edit predictands for each cyclone","html_id":"edit-predictands-for-each-cyclone","implicit":true,"key":"AffXCh3FpR"},{"type":"paragraph","position":{"start":{"line":2,"column":1},"end":{"line":2,"column":1}},"children":[{"type":"text","value":"Here we can move on to our second objective, to explicitly edit the predictands that will be used by the machine learning model. The predictands are the environmental variables associated with a cyclone at each time step. Some of these variables include sea surface temperatures and lower tropospheric humidity.","position":{"start":{"line":2,"column":1},"end":{"line":2,"column":1}},"key":"tXXNeI5uX2"}],"key":"rVVkqUTfRf"}],"key":"kF6hi4Jii6"},{"type":"block","kind":"notebook-code","children":[{"type":"code","lang":"python","executable":true,"value":"def process_row(row, input_dsets):\n    lat = int(row['LAT'])\n    lon = int(row['LON'])\n    time = row['datetime']\n    latmin = lat - 5\n    latmax = lat + 5\n    lonmin = lon - 5\n    lonmax = lon + 5\n\n    try:\n        # Select the data for the given lat/lon/time\n        sel_data = input_dsets.sel(latitude=slice(latmax, latmin), longitude=slice(lonmin, lonmax), time=time)\n    \n    except KeyError:\n        # If data is not found, return None (will be filtered out later)\n        print(f\"Data not found for SID: {row['SID']} at time {time} with lat {lat} and lon {lon}\")\n        return None\n\n    # Add SID and wind speed as new variables\n    sel_data['id'] = row['id']\n    wind_speed = row['USA_WIND']\n\n    # Rename dimensions and set coordinate ranges\n    final_xr = sel_data.rename({'latitude': 'y', 'longitude': 'x'})\n    final_xr['x'] = np.arange(0, len(final_xr['x']), 1)\n    final_xr['y'] = np.arange(0, len(final_xr['y']), 1)\n    final_xr = final_xr.fillna(0)  # Fill NaN values with zeros\n    final_xr['target'] = wind_speed\n\n    return final_xr","key":"gwLc3QLGDk"},{"type":"output","id":"ReHn5ITaumk1VORPhujXj","data":[],"key":"gfLYrdOgIw"}],"key":"hVBnrDhRlh"},{"type":"block","kind":"notebook-code","children":[{"type":"code","lang":"python","executable":true,"value":"# Wrap your row processing in dask.delayed\ndelayed_results = []\nfor index, row in ib_data_processed.iterrows():\n    delayed_result = dask.delayed(process_row)(row, input_dsets)\n    delayed_results.append(delayed_result)\n\n# Compute in parallel and filter out None results\nfinal_data = dask.compute(*delayed_results)\nfinal_data = [ds for ds in final_data if ds is not None]\n\n# Concatenate along 'time' dimension\nfinal_data_xr = xr.concat(final_data, dim='time')","key":"wYNsh1Y0YV"},{"type":"output","id":"ssnrEXQnF3FNaX1s-AA6X","data":[],"key":"HbU9JwxnMX"}],"key":"otRGM84s8R"},{"type":"block","kind":"notebook-content","children":[{"type":"paragraph","position":{"start":{"line":1,"column":1},"end":{"line":1,"column":1}},"children":[{"type":"text","value":"Check out ","position":{"start":{"line":1,"column":1},"end":{"line":1,"column":1}},"key":"Ie6vTtoYzO"},{"type":"link","url":"https://www.markdownguide.org/basic-syntax/","position":{"start":{"line":1,"column":1},"end":{"line":1,"column":1}},"children":[{"type":"strong","position":{"start":{"line":1,"column":1},"end":{"line":1,"column":1}},"children":[{"type":"text","value":"any number of helpful Markdown resources","position":{"start":{"line":1,"column":1},"end":{"line":1,"column":1}},"key":"A4a6t7HnO2"}],"key":"oDxJiGKcde"}],"urlSource":"https://www.markdownguide.org/basic-syntax/","key":"eQ3sSLJCHt"},{"type":"text","value":" for further customizing your notebooks and the ","position":{"start":{"line":1,"column":1},"end":{"line":1,"column":1}},"key":"Hm7uZ84TPq"},{"type":"link","url":"https://mystmd.org/guide/syntax-overview","position":{"start":{"line":1,"column":1},"end":{"line":1,"column":1}},"children":[{"type":"strong","position":{"start":{"line":1,"column":1},"end":{"line":1,"column":1}},"children":[{"type":"text","value":"MyST Syntax Overview","position":{"start":{"line":1,"column":1},"end":{"line":1,"column":1}},"key":"hEJEwaeDXK"}],"key":"peGc6qb7TI"}],"urlSource":"https://mystmd.org/guide/syntax-overview","key":"FMERmQUNca"},{"type":"text","value":" for MyST-specific formatting information. Don’t hesitate to ask questions if you have problems getting it to look ","position":{"start":{"line":1,"column":1},"end":{"line":1,"column":1}},"key":"fLBrxmpCja"},{"type":"emphasis","position":{"start":{"line":1,"column":1},"end":{"line":1,"column":1}},"children":[{"type":"text","value":"just right","position":{"start":{"line":1,"column":1},"end":{"line":1,"column":1}},"key":"VOEYElWI93"}],"key":"X25PjQM68k"},{"type":"text","value":".","position":{"start":{"line":1,"column":1},"end":{"line":1,"column":1}},"key":"WcNt4Zg3sz"}],"key":"MR08WK2wBD"}],"key":"bI0jMOaifr"},{"type":"block","kind":"notebook-content","children":[{"type":"heading","depth":2,"position":{"start":{"line":1,"column":1},"end":{"line":1,"column":1}},"children":[{"type":"text","value":"Last Section","position":{"start":{"line":1,"column":1},"end":{"line":1,"column":1}},"key":"hUtgkOF9d0"}],"identifier":"last-section","label":"Last Section","html_id":"last-section","implicit":true,"key":"CN1X5GiOr5"},{"type":"paragraph","position":{"start":{"line":3,"column":1},"end":{"line":3,"column":1}},"children":[{"type":"text","value":"You can add ","position":{"start":{"line":3,"column":1},"end":{"line":3,"column":1}},"key":"eN0AFP7ycM"},{"type":"link","url":"https://mystmd.org/guide/admonitions","position":{"start":{"line":3,"column":1},"end":{"line":3,"column":1}},"children":[{"type":"text","value":"admonitions using MyST syntax","position":{"start":{"line":3,"column":1},"end":{"line":3,"column":1}},"key":"ezPpLfgwzV"}],"urlSource":"https://mystmd.org/guide/admonitions","key":"Kbt6TirWYE"},{"type":"text","value":":","position":{"start":{"line":3,"column":1},"end":{"line":3,"column":1}},"key":"tVXxNPJDhS"}],"key":"YvcwEemicM"}],"key":"YunfXXItI9"},{"type":"block","kind":"notebook-content","children":[{"type":"admonition","kind":"note","children":[{"type":"admonitionTitle","children":[{"type":"text","value":"Note","key":"TH6jnVAd4r"}],"key":"O3hwakLZWU"},{"type":"paragraph","position":{"start":{"line":2,"column":1},"end":{"line":2,"column":1}},"children":[{"type":"text","value":"Your relevant information here!","position":{"start":{"line":2,"column":1},"end":{"line":2,"column":1}},"key":"vIN6NDQCis"}],"key":"OMfev5tWnm"}],"key":"M6kThYp56c"}],"key":"rweFULDfM8"},{"type":"block","kind":"notebook-content","children":[{"type":"paragraph","position":{"start":{"line":1,"column":1},"end":{"line":1,"column":1}},"children":[{"type":"text","value":"Some other admonitions you can put in (","position":{"start":{"line":1,"column":1},"end":{"line":1,"column":1}},"key":"fD4DZC8dNw"},{"type":"link","url":"https://mystmd.org/guide/admonitions#admonitions-list","position":{"start":{"line":1,"column":1},"end":{"line":1,"column":1}},"children":[{"type":"text","value":"there are 10 total","position":{"start":{"line":1,"column":1},"end":{"line":1,"column":1}},"key":"Dgqs5varNA"}],"urlSource":"https://mystmd.org/guide/admonitions#admonitions-list","key":"ea0EAqpG0T"},{"type":"text","value":"):","position":{"start":{"line":1,"column":1},"end":{"line":1,"column":1}},"key":"pYzlHPEq0U"}],"key":"o4L9ZmSh7U"}],"key":"u0a5ym59fh"},{"type":"block","kind":"notebook-content","children":[{"type":"admonition","kind":"hint","children":[{"type":"admonitionTitle","children":[{"type":"text","value":"Hint","key":"SeRl0HkbVw"}],"key":"KrtVfXNlwo"},{"type":"paragraph","position":{"start":{"line":2,"column":1},"end":{"line":2,"column":1}},"children":[{"type":"text","value":"A helpful hint.","position":{"start":{"line":2,"column":1},"end":{"line":2,"column":1}},"key":"SjpgXkLHCs"}],"key":"nojqn8NtJY"}],"key":"BkWgmdF94E"}],"key":"QM4yaolf2P"},{"type":"block","kind":"notebook-content","children":[{"type":"admonition","kind":"warning","children":[{"type":"admonitionTitle","children":[{"type":"text","value":"Warning","key":"UUo14qpp8s"}],"key":"OWvfmFQ0m6"},{"type":"paragraph","position":{"start":{"line":2,"column":1},"end":{"line":2,"column":1}},"children":[{"type":"text","value":"Be careful!","position":{"start":{"line":2,"column":1},"end":{"line":2,"column":1}},"key":"jtRYptuwp5"}],"key":"hHNuatTKyK"}],"key":"US8izU1lJE"}],"key":"PyhgLDl3uV"},{"type":"block","kind":"notebook-content","children":[{"type":"admonition","kind":"danger","children":[{"type":"admonitionTitle","children":[{"type":"text","value":"Danger","key":"WNsgEL5th1"}],"key":"KC40RTJzEJ"},{"type":"paragraph","position":{"start":{"line":2,"column":1},"end":{"line":2,"column":1}},"children":[{"type":"text","value":"Scary stuff be here.","position":{"start":{"line":2,"column":1},"end":{"line":2,"column":1}},"key":"EKgHLfL8qM"}],"key":"jjg317tD7T"}],"key":"XIXMgBqIQ1"}],"key":"sqA3aAxYbA"},{"type":"block","kind":"notebook-content","children":[{"type":"paragraph","position":{"start":{"line":1,"column":1},"end":{"line":1,"column":1}},"children":[{"type":"text","value":"We also suggest checking out Jupyter Book’s ","position":{"start":{"line":1,"column":1},"end":{"line":1,"column":1}},"key":"m7358mJPLV"},{"type":"link","url":"https://jupyterbook.org/content/metadata.html#jupyter-cell-tags","position":{"start":{"line":1,"column":1},"end":{"line":1,"column":1}},"children":[{"type":"text","value":"brief demonstration","position":{"start":{"line":1,"column":1},"end":{"line":1,"column":1}},"key":"Riedz9XKfJ"}],"urlSource":"https://jupyterbook.org/content/metadata.html#jupyter-cell-tags","key":"qPsbGbMbzk"},{"type":"text","value":" on adding cell tags to your cells in Jupyter Notebook, Lab, or manually. Using these cell tags can allow you to ","position":{"start":{"line":1,"column":1},"end":{"line":1,"column":1}},"key":"QXAQxakHTK"},{"type":"link","url":"https://jupyterbook.org/interactive/hiding.html","position":{"start":{"line":1,"column":1},"end":{"line":1,"column":1}},"children":[{"type":"text","value":"customize","position":{"start":{"line":1,"column":1},"end":{"line":1,"column":1}},"key":"qV5V982ZjX"}],"urlSource":"https://jupyterbook.org/interactive/hiding.html","key":"Fym97258Jg"},{"type":"text","value":" how your code content is displayed and even ","position":{"start":{"line":1,"column":1},"end":{"line":1,"column":1}},"key":"cSU2bUgT17"},{"type":"link","url":"https://jupyterbook.org/content/execute.html#dealing-with-code-that-raises-errors","position":{"start":{"line":1,"column":1},"end":{"line":1,"column":1}},"children":[{"type":"text","value":"demonstrate errors","position":{"start":{"line":1,"column":1},"end":{"line":1,"column":1}},"key":"dU8uUIkdc6"}],"urlSource":"https://jupyterbook.org/content/execute.html#dealing-with-code-that-raises-errors","key":"LuxHbIMNfE"},{"type":"text","value":" without altogether crashing our loyal army of machines!","position":{"start":{"line":1,"column":1},"end":{"line":1,"column":1}},"key":"IFxkiZ2tNK"}],"key":"CbMvnAH8lG"}],"key":"nGoFzYKLnv"},{"type":"block","kind":"notebook-content","children":[{"type":"thematicBreak","position":{"start":{"line":1,"column":1},"end":{"line":1,"column":1}},"key":"bgcrzA1FBa"}],"key":"bFDL0UuD51"},{"type":"block","kind":"notebook-content","children":[{"type":"heading","depth":2,"position":{"start":{"line":1,"column":1},"end":{"line":1,"column":1}},"children":[{"type":"text","value":"Summary","position":{"start":{"line":1,"column":1},"end":{"line":1,"column":1}},"key":"F6p1NFMWiY"}],"identifier":"summary","label":"Summary","html_id":"summary","implicit":true,"key":"JfPEcKZQSH"},{"type":"paragraph","position":{"start":{"line":2,"column":1},"end":{"line":2,"column":1}},"children":[{"type":"text","value":"Add one final ","position":{"start":{"line":2,"column":1},"end":{"line":2,"column":1}},"key":"DSMUxoUscs"},{"type":"inlineCode","value":"---","position":{"start":{"line":2,"column":1},"end":{"line":2,"column":1}},"key":"u0ByxFuFn0"},{"type":"text","value":" marking the end of your body of content, and then conclude with a brief single paragraph summarizing at a high level the key pieces that were learned and how they tied to your objectives. Look to reiterate what the most important takeaways were.","position":{"start":{"line":2,"column":1},"end":{"line":2,"column":1}},"key":"SmHf6PDxPL"}],"key":"RbNlCxPEqN"},{"type":"heading","depth":3,"position":{"start":{"line":4,"column":1},"end":{"line":4,"column":1}},"children":[{"type":"text","value":"What’s next?","position":{"start":{"line":4,"column":1},"end":{"line":4,"column":1}},"key":"WqlHzB9EyO"}],"identifier":"whats-next","label":"What’s next?","html_id":"whats-next","implicit":true,"key":"bTaNbG3Wk2"},{"type":"paragraph","position":{"start":{"line":5,"column":1},"end":{"line":5,"column":1}},"children":[{"type":"text","value":"Let Jupyter book tie this to the next (sequential) piece of content that people could move on to down below and in the sidebar. However, if this page uniquely enables your reader to tackle other nonsequential concepts throughout this book, or even external content, link to it here!","position":{"start":{"line":5,"column":1},"end":{"line":5,"column":1}},"key":"vIFeKUHfRW"}],"key":"u2VEPmptAI"}],"key":"Qsn4KpLbcb"},{"type":"block","kind":"notebook-content","children":[{"type":"heading","depth":2,"position":{"start":{"line":1,"column":1},"end":{"line":1,"column":1}},"children":[{"type":"text","value":"Resources and references","position":{"start":{"line":1,"column":1},"end":{"line":1,"column":1}},"key":"ewM0dbcEIW"}],"identifier":"resources-and-references","label":"Resources and references","html_id":"resources-and-references","implicit":true,"key":"o4vfzvnJbw"},{"type":"paragraph","position":{"start":{"line":2,"column":1},"end":{"line":2,"column":1}},"children":[{"type":"text","value":"Finally, be rigorous in your citations and references as necessary. Give credit where credit is due. Also, feel free to link to relevant external material, further reading, documentation, etc. Then you’re done! Give yourself a quick review, a high five, and send us a pull request. A few final notes:","position":{"start":{"line":2,"column":1},"end":{"line":2,"column":1}},"key":"Qnb3IadmvC"}],"key":"NXc1P8YGg2"},{"type":"list","ordered":false,"spread":false,"position":{"start":{"line":3,"column":1},"end":{"line":8,"column":1}},"children":[{"type":"listItem","spread":true,"position":{"start":{"line":3,"column":1},"end":{"line":3,"column":1}},"children":[{"type":"inlineCode","value":"Kernel > Restart Kernel and Run All Cells...","position":{"start":{"line":3,"column":1},"end":{"line":3,"column":1}},"key":"iVUnKfm7mX"},{"type":"text","value":" to confirm that your notebook will cleanly run from start to finish","position":{"start":{"line":3,"column":1},"end":{"line":3,"column":1}},"key":"JT5KTPaGvb"}],"key":"UZMAkHbAmD"},{"type":"listItem","spread":true,"position":{"start":{"line":4,"column":1},"end":{"line":4,"column":1}},"children":[{"type":"inlineCode","value":"Kernel > Restart Kernel and Clear All Outputs...","position":{"start":{"line":4,"column":1},"end":{"line":4,"column":1}},"key":"n8bsamdeQF"},{"type":"text","value":" before committing your notebook, our machines will do the heavy lifting","position":{"start":{"line":4,"column":1},"end":{"line":4,"column":1}},"key":"wz4S19FP3m"}],"key":"DKGbLZarQF"},{"type":"listItem","spread":true,"position":{"start":{"line":5,"column":1},"end":{"line":5,"column":1}},"children":[{"type":"text","value":"Take credit! Provide author contact information if you’d like; if so, consider adding information here at the bottom of your notebook","position":{"start":{"line":5,"column":1},"end":{"line":5,"column":1}},"key":"qI8VuKE6HL"}],"key":"TkoNA5gRYa"},{"type":"listItem","spread":true,"position":{"start":{"line":6,"column":1},"end":{"line":6,"column":1}},"children":[{"type":"text","value":"Give credit! Attribute appropriate authorship for referenced code, information, images, etc.","position":{"start":{"line":6,"column":1},"end":{"line":6,"column":1}},"key":"tKAJSNnUzB"}],"key":"PPuhZN9HAx"},{"type":"listItem","spread":true,"position":{"start":{"line":7,"column":1},"end":{"line":8,"column":1}},"children":[{"type":"text","value":"Only include what you’re legally allowed: ","position":{"start":{"line":7,"column":1},"end":{"line":7,"column":1}},"key":"zZonmE6jgp"},{"type":"strong","position":{"start":{"line":7,"column":1},"end":{"line":7,"column":1}},"children":[{"type":"text","value":"no copyright infringement or plagiarism","position":{"start":{"line":7,"column":1},"end":{"line":7,"column":1}},"key":"lNQDIiayey"}],"key":"AVHRIhAXFI"}],"key":"SXeBIz8GXC"}],"key":"JdZE8R9WoN"},{"type":"paragraph","position":{"start":{"line":9,"column":1},"end":{"line":9,"column":1}},"children":[{"type":"text","value":"Thank you for your contribution!","position":{"start":{"line":9,"column":1},"end":{"line":9,"column":1}},"key":"Zg6ilRnR97"}],"key":"PWHdP13Udu"}],"key":"wN0imhfuBi"}],"key":"B0vl6cX9Zh"},"references":{"cite":{"order":[],"data":{}}},"footer":{"navigation":{"prev":{"title":"Preprocess IBTRACK data","url":"/notebooks/ibtrack-preprocessing","group":"Data Preprocessing"}}},"domain":"http://localhost:3000"}